pgmigrations/__init__.py
pgmigrations/api.py
pgmigrations/cli.py
pgmigrations/constants.py
pgmigrations/data_access.py
pgmigrations/exceptions.py
pgmigrations/version.py
pgmigrations/migrations/20200701_0000_migration_create_migration_table/apply.sql
pgmigrations/migrations/20200701_0000_migration_create_migration_table/rollback.sql
pgmigrations-0.0.13.dist-info/LICENSE
pgmigrations-0.0.13.dist-info/METADATA
pgmigrations-0.0.13.dist-info/WHEEL
pgmigrations-0.0.13.dist-info/entry_points.txt
pgmigrations-0.0.13.dist-info/top_level.txt
pgmigrations-0.0.13.dist-info/RECORD
