Metadata-Version: 2.1
Name: pgmigrations
Version: 0.0.13
Summary: SQL migrations for projects using PostgreSQL
Home-page: https://github.com/peajayni/pgmigrations
License: UNKNOWN
Platform: UNKNOWN
Requires-Python: >=3.6
Requires-Dist: click
Requires-Dist: psycopg2-binary
Requires-Dist: cached-property
